snappi_convergence/__init__.py
snappi_convergence/otgconvergence_pb2.py
snappi_convergence/otgconvergence_pb2_grpc.py
snappi_convergence/snappi_convergence.py
snappi_convergence-0.4.1.dist-info/METADATA
snappi_convergence-0.4.1.dist-info/WHEEL
snappi_convergence-0.4.1.dist-info/top_level.txt
snappi_convergence-0.4.1.dist-info/RECORD
