Metadata-Version: 2.1
Name: snappi-convergence
Version: 0.4.1
Summary: A snappi extension for measuring network convergence
Home-page: https://github.com/open-traffic-generator/snappi-convergence
Author: Open Traffic Generator
Author-email: ashutshkumr@gmail.com
License: MIT
Keywords: snappi testing open traffic generator automation
Platform: UNKNOWN
Classifier: Development Status :: 3 - Alpha
Classifier: Intended Audience :: Developers
Classifier: Topic :: Software Development :: Testing :: Traffic Generation
Classifier: License :: OSI Approved :: MIT License
Classifier: Programming Language :: Python :: 2.7
Classifier: Programming Language :: Python :: 3
Requires-Python: >=2.7, <4
Requires-Dist: PyYAML
Requires-Dist: requests
Requires-Dist: urllib3
Requires-Dist: protobuf (==3.15.0) ; python_version <= "3.6"
Requires-Dist: grpcio (==1.35.0) ; python_version == "2.7"
Requires-Dist: grpcio-tools (==1.35.0) ; python_version == "2.7"
Requires-Dist: grpcio (==1.44.0) ; python_version > "2.7"
Requires-Dist: grpcio-tools (==1.44.0) ; python_version > "2.7"
Requires-Dist: protobuf (==3.20.1) ; python_version > "3.6"
Provides-Extra: testing
Requires-Dist: pytest ; extra == 'testing'
